README.md
setup.cfg
setup.py
syncanysql/__init__.py
syncanysql/compiler.py
syncanysql/config.py
syncanysql/errors.py
syncanysql/executor.py
syncanysql/main.py
syncanysql/parser.py
syncanysql/prompt.py
syncanysql/utils.py
syncanysql/version.py
syncanysql.egg-info/PKG-INFO
syncanysql.egg-info/SOURCES.txt
syncanysql.egg-info/dependency_links.txt
syncanysql.egg-info/entry_points.txt
syncanysql.egg-info/not-zip-safe
syncanysql.egg-info/requires.txt
syncanysql.egg-info/top_level.txt
syncanysql/calculaters/__init__.py
syncanysql/calculaters/aggregate_calculater.py
syncanysql/calculaters/env_variable_calculater.py
syncanysql/calculaters/generate_calculater.py
syncanysql/calculaters/mysql_calculater.py
syncanysql/calculaters/pyeval_calculater.py
syncanysql/calculaters/query_tasker_calculater.py
syncanysql/calculaters/row_calculater.py
syncanysql/calculaters/window_calculater.py
syncanysql/calculaters/mysql_funcs/__init__.py
syncanysql/calculaters/mysql_funcs/datetime_funcs.py
syncanysql/calculaters/mysql_funcs/json_funcs.py
syncanysql/calculaters/mysql_funcs/logical_funcs.py
syncanysql/calculaters/mysql_funcs/number_funcs.py
syncanysql/calculaters/mysql_funcs/regexp_funcs.py
syncanysql/calculaters/mysql_funcs/string_funcs.py
syncanysql/taskers/__init__.py
syncanysql/taskers/delete.py
syncanysql/taskers/execute.py
syncanysql/taskers/explain.py
syncanysql/taskers/into.py
syncanysql/taskers/query.py
syncanysql/taskers/set.py
syncanysql/taskers/show.py
syncanysql/taskers/use.py