Metadata-Version: 2.1
Name: syncanysql
Version: 0.1.27
Summary: Simple and easy-to-use sql execution engine
Home-page: https://github.com/snower/syncany-sql
Author: snower
Author-email: sujian199@gmail.com
License: MIT
Platform: UNKNOWN
Provides-Extra: clickhouse
Provides-Extra: elasticsearch
Provides-Extra: influxdb
Provides-Extra: openpyxl
Provides-Extra: postgresql
Provides-Extra: prql-python
Provides-Extra: pymongo
Provides-Extra: pymssql
Provides-Extra: pymysql
Provides-Extra: redis
Provides-Extra: requests
